stackcoin/__init__.py
stackcoin/exceptions.py
stackcoin-0.0.1.dist-info/LICENSE
stackcoin-0.0.1.dist-info/METADATA
stackcoin-0.0.1.dist-info/WHEEL
stackcoin-0.0.1.dist-info/top_level.txt
stackcoin-0.0.1.dist-info/RECORD
