Metadata-Version: 2.1
Name: stackcoin
Version: 0.0.1
Summary: Python client for interacting with the StackCoin HTTP API
Home-page: https://github.com/jackharrhy/stackcoin-python
Author: Jack Arthur Harrhy
Author-email: me@jackharrhy.com
License: UNKNOWN
Platform: UNKNOWN
Classifier: Programming Language :: Python :: 3
Classifier: License :: OSI Approved :: MIT License
Classifier: Operating System :: OS Independent
Requires-Python: >=3.6
Requires-Dist: pydantic (>=1)
Requires-Dist: requests (>=2)
